{
 "sha1": "9adfe02643ded630ab9ac953da828f39442815df",
 "lic": "pd",
 "url": "https://upload.wikimedia.org/wikipedia/en/b/b7/La_Orquesta_T%C3%ADpica_de_la_Ciudad_de_M%C3%A9xico.png",
 "ext": "png",
 "from": "wiki",
 "created": 1458507658,
 "name": "La Orquesta Típica de la Ciudad de México",
 "desc": {
  "url": "https://en.wikipedia.org/w/index.php?curid=47776224",
  "html": "<p>Mexican Typical Orchiestra or La Orquesta Típica de la Ciudad de México in Columbus, Ohio on their United States Tour in 1885.\n</p>"
 }
}