{
 "sha1": "53c513eb7720567343c6c710b21995e4cc752bcf",
 "lic": "pd",
 "url": "https://upload.wikimedia.org/wikipedia/en/e/ee/US_Army_116th_Military_Intelligence_Brigade_SSI.png",
 "ext": "png",
 "from": "wiki",
 "created": 1458507660,
 "name": "US Army 116th Military Intelligence Brigade SSI",
 "desc": {
  "url": "https://en.wikipedia.org/w/index.php?curid=48690018",
  "html": "<p>The <a href=\"//en.wikipedia.org/wiki/U.S._Army\" title=\"U.S. Army\" class=\"mw-redirect\">U.S. Army</a>'s <a href=\"//en.wikipedia.org/w/index.php?title=116th_Military_Intelligence_Brigade_(United_States)&amp;action=edit&amp;redlink=1\" class=\"new\" title=\"116th Military Intelligence Brigade (United States) (page does not exist)\">116th Military Intelligence Brigade</a> <a href=\"//en.wikipedia.org/wiki/Shoulder_Sleeve_Insignia\" title=\"Shoulder Sleeve Insignia\" class=\"mw-redirect\">Shoulder Sleeve Insignia</a>\n</p>"
 },
 "tags": [
  "img:png24 better than jpeg90",
  "united states army institute of heraldry images",
  "img:png8 better than jpeg90",
  "img:png8 better than jpeg75"
 ]
}