{
 "sha1": "eb9335e2d83cd919afe7a5799b70fe5693650d6d",
 "lic": "pd",
 "url": "https://images.unsplash.com/photo-1432879897648-f9d45b2ec678",
 "urls": [
  "https://unsplash.com/photos/T8I3UuK-QXY/download",
  "https://images.unsplash.com/photo-1432879897648-f9d45b2ec678?ixlib=rb-0.3.5&q=80&fm=jpg&crop=entropy&s=23202a129745942e2d23036893bf4cd7"
 ],
 "ext": "jpeg",
 "from": "findaphoto",
 "created": 1456917504,
 "tags": [
  "img:exif",
  "cloud",
  "country",
  "countryside",
  "field",
  "grass",
  "harvest",
  "hill",
  "horizon",
  "landscape",
  "meadow",
  "mountain",
  "nature",
  "outdoors",
  "rural",
  "sky",
  "summer",
  "travel",
  "tree",
  "tuscany"
 ]
}