{
 "sha1": "f1ec64e6eb451abe7e00d381970a0bec800eb84d",
 "lic": "pd",
 "url": "https://upload.wikimedia.org/wikipedia/en/3/3b/Haidar_Pasha_Jami.png",
 "ext": "png",
 "from": "wiki",
 "created": 1458507658,
 "name": "Haidar Pasha Jami",
 "desc": {
  "url": "https://en.wikipedia.org/w/index.php?curid=40736404",
  "html": "<p>Original drawing of Haidar Pasha mosque by Louis Salvator (publ.1881 in \"Levkosia Capital of Cyprus\")\n</p>"
 },
 "tags": [
  "img:png8 better than jpeg90",
  "img:png8 better than jpeg75",
  "img:png8 lossless"
 ]
}