{
 "sha1": "2b239cba39c7ff91f8cddd12ab9c38e938916dd5",
 "lic": "pd",
 "url": "https://images.unsplash.com/photo-1415226556993-1404e0c6e727",
 "urls": [
  "https://unsplash.com/photos/jTeQavJjBDs/download",
  "https://images.unsplash.com/photo-1415226556993-1404e0c6e727?ixlib=rb-0.3.5&q=80&fm=jpg&crop=entropy&s=01cfeeb11e880877517310cb66cbed2f"
 ],
 "ext": "jpeg",
 "from": "findaphoto",
 "created": 1456918016,
 "tags": [
  "bath",
  "bathe",
  "bathing",
  "hill",
  "holiday",
  "mountain",
  "people",
  "pool",
  "rock",
  "spa",
  "steam",
  "stone",
  "swimming",
  "vacation",
  "water"
 ]
}