{
 "sha1": "c1a22ef24e206a5077bc8bc41188bb6acb1e8d57",
 "lic": "pd",
 "url": "https://images.unsplash.com/photo-1431683535750-2b9b2371efb7",
 "urls": [
  "https://unsplash.com/photos/ywMwEYTlObQ/download",
  "https://images.unsplash.com/photo-1431683535750-2b9b2371efb7?ixlib=rb-0.3.5&q=80&fm=jpg&crop=entropy&s=fdbba5e18b0b16d1052b33a93e9dc722"
 ],
 "ext": "jpeg",
 "from": "findaphoto",
 "created": 1456878961,
 "tags": [
  "agriculture",
  "countryside",
  "cropland",
  "evening",
  "farm",
  "field",
  "grass",
  "grassland",
  "hill",
  "horizon",
  "landscape",
  "meadow",
  "morning",
  "nature",
  "outdoors",
  "prairie",
  "sky",
  "sunset",
  "tree"
 ]
}