{
 "sha1": "02617a589dd7f2105b71164c83cbb7262bae47c3",
 "lic": "pd",
 "url": "https://images.unsplash.com/photo-1453224475513-988475ec1e59",
 "urls": [
  "https://unsplash.com/photos/D6sF071Cmds/download",
  "https://images.unsplash.com/photo-1453224475513-988475ec1e59?ixlib=rb-0.3.5&q=80&fm=jpg&crop=entropy&s=134538b69d9c9f33f2b41ec2e52498c4"
 ],
 "ext": "jpeg",
 "from": "findaphoto",
 "created": 1456903947,
 "tags": [
  "autumn",
  "blur",
  "card",
  "decoration",
  "dof",
  "fall",
  "flower",
  "food",
  "garden",
  "leaves",
  "light",
  "medicine",
  "nature",
  "outdoors",
  "people",
  "still life",
  "summer",
  "tea",
  "tree",
  "wood"
 ]
}