{
 "sha1": "02f30325c736e4b0dcb97f46eb7b5f7c936c9b02",
 "lic": "cc0",
 "url": "https://upload.wikimedia.org/wikipedia/en/d/d9/Barcelona_passport_stamps.png",
 "ext": "png",
 "from": "wiki",
 "created": 1458507657,
 "name": "Barcelona passport stamps",
 "desc": {
  "url": "https://en.wikipedia.org/w/index.php?curid=35820483",
  "html": "<p>entry and exit passport stamps from Barcelona, as seen in a US passport\n</p>"
 },
 "wiki": {
  "DateTime": "2012-05-14 20:08:36",
  "Credit": "<p>I took this photo<br><b>Previously published:</b>\n</p>",
  "DateTimeOriginal": "<p>2012-05-14\n</p>",
  "Artist": "<p><a href=\"//en.wikipedia.org/wiki/User:Monocletophat123\" title=\"User:Monocletophat123\">Monocletophat123</a>\n</p>",
  "UsageTerms": "Creative Commons Zero, Public Domain Dedication",
  "AttributionRequired": "false",
  "LicenseUrl": "creativecommons.org/publicdomain/zero/1.0/deed.en"
 }
}