{
 "sha1": "d0a5b1ff9b860fa493e2c0fbed573915cb053e13",
 "lic": "pd",
 "url": "https://images.unsplash.com/reserve/fqUehZ3ZRru2Kh11qDBT_IMG_0042.jpg",
 "urls": [
  "https://unsplash.com/photos/leHDA08Lbpc/download",
  "https://images.unsplash.com/reserve/fqUehZ3ZRru2Kh11qDBT_IMG_0042.jpg?ixlib=rb-0.3.5&q=80&fm=jpg&crop=entropy&s=25e2bb6fa92604b660611f684d19f8af"
 ],
 "ext": "jpeg",
 "from": "findaphoto",
 "created": 1456917051,
 "name": "IMG 0042",
 "tags": [
  "beach",
  "boat",
  "bridge",
  "chair",
  "dusk",
  "island",
  "jetty",
  "lake",
  "landscape",
  "morning",
  "nature",
  "ocean",
  "pier",
  "sea",
  "seat",
  "sky",
  "summer",
  "sun",
  "sunrise",
  "sunset",
  "transport",
  "water"
 ]
}