{
 "sha1": "e3d7d55933c27ffdfc2aa3da58c491c8760cc810",
 "lic": "pd",
 "url": "https://images.unsplash.com/photo-1437650128481-845e6e35bd75",
 "urls": [
  "https://unsplash.com/photos/AekHfFqOtgU/download",
  "https://images.unsplash.com/photo-1437650128481-845e6e35bd75?ixlib=rb-0.3.5&q=80&fm=jpg&crop=entropy&s=f6bb1d6f078dbf26232de27f99637702"
 ],
 "ext": "jpeg",
 "from": "findaphoto",
 "created": 1456917749,
 "tags": [
  "daytime",
  "desert",
  "dusk",
  "evening",
  "hill",
  "landscape",
  "mountain",
  "nature",
  "outdoors",
  "panoramic",
  "remote",
  "rock",
  "scenic",
  "sky",
  "sunrise",
  "sunset",
  "sunshine",
  "travel",
  "valley"
 ]
}