{
 "sha1": "f22071b9d229946795ef8a79add56ca99c09cc5a",
 "lic": "cc-by-sa-3.0",
 "url": "https://upload.wikimedia.org/wikipedia/en/b/b0/BradImes.png",
 "ext": "png",
 "from": "wiki",
 "created": 1458507657,
 "name": "BradImes",
 "desc": {
  "url": "https://en.wikipedia.org/w/index.php?curid=13101909"
 },
 "wiki": {
  "DateTime": "2007-09-05 02:00:27",
  "UsageTerms": "Creative Commons Attribution-ShareAlike 3.0",
  "AttributionRequired": "true",
  "LicenseUrl": "http://creativecommons.org/licenses/by-sa/3.0/"
 }
}