{
 "sha1": "7beab1996eb4efc44a79de54d9ba8fea0b50d485",
 "lic": "cc-by-3.0",
 "url": "https://upload.wikimedia.org/wikipedia/en/b/b6/Childrens_wish_Cutco.png",
 "ext": "png",
 "from": "wiki",
 "created": 1458507657,
 "name": "Childrens wish Cutco",
 "desc": {
  "url": "https://en.wikipedia.org/w/index.php?curid=30205664"
 },
 "wiki": {
  "DateTime": "2010-12-27 05:46:25",
  "UsageTerms": "Creative Commons Attribution 3.0",
  "AttributionRequired": "true",
  "LicenseUrl": "http://creativecommons.org/licenses/by/3.0/"
 }
}