{
 "sha1": "28cbc082d67b4b5d0c29d4d9cb1eb59a8c06c90a",
 "lic": "pd",
 "url": "https://farm6.staticflickr.com/5686/22454138805_8d980faa81_o.jpg",
 "urls": [
  "https://farm6.staticflickr.com/5686/22454138805_8d980faa81_o.jpg"
 ],
 "ext": "jpeg",
 "from": "findaphoto",
 "created": 1456917935,
 "tags": [
  "adult",
  "ancient",
  "architecture",
  "art",
  "cathedral",
  "church",
  "decoration",
  "detail",
  "face",
  "fine art",
  "lion",
  "palace",
  "pattern",
  "people",
  "religion",
  "sculpture",
  "statue",
  "symbol",
  "travel",
  "img:png8 lossless"
 ]
}