{
 "sha1": "6e3488c5109960df3cdfaf09485dd8e161e9633a",
 "lic": "cc-by-sa-3.0",
 "url": "https://upload.wikimedia.org/wikipedia/en/b/b7/Rhino_hornbill.png",
 "ext": "png",
 "from": "wiki",
 "created": 1458507659,
 "name": "Rhino hornbill",
 "desc": {
  "url": "https://en.wikipedia.org/w/index.php?curid=19874514",
  "html": "<a href=\"//en.wikipedia.org/wiki/Chester_Zoo\" title=\"Chester Zoo\">Chester Zoo</a>\n<p><a href=\"//en.wikipedia.org/wiki/Rhinoceros_Hornbill\" title=\"Rhinoceros Hornbill\" class=\"mw-redirect\">Rhinoceros Hornbill</a> (Buceros rhinoceros)\n</p>"
 },
 "wiki": {
  "DateTime": "2008-03-17 18:05:23",
  "Credit": "<p>self-made\n</p>",
  "DateTimeOriginal": "<p>2007-03-14\n</p>",
  "Artist": "<p><a href=\"//en.wikipedia.org/wiki/User:Neil\" title=\"User:Neil\" class=\"mw-redirect\"><u style=\"text-decoration:none;font:100% cursive;color:#060\">Neıl</u></a> <a href=\"//en.wikipedia.org/wiki/User_talk:Neil\" title=\"User talk:Neil\" class=\"mw-redirect\"><u style=\"text-decoration:none;color:#060\">☎</u></a>\n</p>",
  "UsageTerms": "Creative Commons Attribution-ShareAlike 3.0",
  "AttributionRequired": "true",
  "LicenseUrl": "http://creativecommons.org/licenses/by-sa/3.0/"
 }
}