{
 "sha1": "c505a83e725dc4df2d896197de8427f248c3fe1f",
 "lic": "pd",
 "url": "https://images.unsplash.com/photo-1415604934674-561df9abf539",
 "urls": [
  "https://unsplash.com/photos/ZMZHcvIVgbg/download",
  "https://images.unsplash.com/photo-1415604934674-561df9abf539?ixlib=rb-0.3.5&q=80&fm=jpg&crop=entropy&s=f0dc1d823d4e4b64f6ceed434362318a"
 ],
 "ext": "jpeg",
 "from": "findaphoto",
 "created": 1456879661,
 "tags": [
  "antique",
  "business",
  "classic",
  "conceptual",
  "direction",
  "discovery",
  "exploration",
  "guidance",
  "hours",
  "latitude",
  "longitude",
  "lost",
  "navigation",
  "old",
  "orientation",
  "retro",
  "time",
  "vintage",
  "west"
 ]
}