{
 "sha1": "ff17e7363737fc5a81599165914a5a81b62f75d9",
 "lic": "pd",
 "url": "https://upload.wikimedia.org/wikipedia/en/4/4b/Albert_Einstein_by_Suse_Byk.png",
 "ext": "png",
 "from": "wiki",
 "created": 1458507657,
 "name": "Albert Einstein by Suse Byk",
 "desc": {
  "url": "https://en.wikipedia.org/w/index.php?curid=20805315",
  "html": "<p>Front page of the <i><a href=\"//de.wikipedia.org/wiki/Berliner_Illustrirte_Zeitung\" class=\"extiw\" title=\"de:Berliner Illustrirte Zeitung\">Berliner Illustrirte Zeitung</a></i> of December 14, 1919 with a portrait of <a href=\"//en.wikipedia.org/wiki/Albert_Einstein\" title=\"Albert Einstein\">Albert Einstein</a>.\n</p>"
 },
 "tags": [
  "img:gray",
  "img:color profile",
  "img:png8 lossless"
 ]
}