{
 "sha1": "77a3bf7329580e0af598e54ab03ecd008382b0d8",
 "lic": "pd",
 "url": "https://images.unsplash.com/photo-1452088366484-78262ddbe7ab",
 "urls": [
  "https://unsplash.com/photos/2ItDEHBwQjE/download",
  "https://images.unsplash.com/photo-1452088366484-78262ddbe7ab?ixlib=rb-0.3.5&q=80&fm=jpg&crop=entropy&s=de87a8e4cd52eaadbdec8a409253d210"
 ],
 "ext": "jpeg",
 "from": "findaphoto",
 "created": 1456881632,
 "tags": [
  "img:compressed",
  "background",
  "bank",
  "business",
  "capital",
  "city",
  "commerce",
  "design",
  "economy",
  "exchange",
  "finance",
  "financial",
  "growth",
  "high",
  "industrial",
  "industry",
  "market",
  "monetary",
  "money",
  "office",
  "success",
  "urban",
  "wealth"
 ]
}