{
 "sha1": "a564ef8616471517b68418c4f20b632a904ee5a1",
 "lic": "pd",
 "url": "https://images.unsplash.com/photo-1444167827109-712640e22c8e",
 "urls": [
  "https://unsplash.com/photos/SJX2o-eItXY/download",
  "https://images.unsplash.com/photo-1444167827109-712640e22c8e?ixlib=rb-0.3.5&q=80&fm=jpg&crop=entropy&s=d1cbce62c09089dbe677fc24001be6f3"
 ],
 "ext": "jpeg",
 "from": "findaphoto",
 "created": 1456906203,
 "tags": [
  "animal",
  "art",
  "beach",
  "black and white",
  "bridge",
  "cat",
  "child",
  "crown",
  "figure",
  "fine art",
  "girl",
  "grey",
  "love",
  "monochrome",
  "people",
  "person",
  "portrait",
  "road",
  "sculpture",
  "statue",
  "still life",
  "street",
  "travel",
  "woman"
 ]
}