{
 "sha1": "e2b48e0d62496658048e0ce5ccb3ba6793804385",
 "lic": "pd",
 "url": "https://images.unsplash.com/uploads/14122811862445bc266cf/931448f2",
 "urls": [
  "https://unsplash.com/photos/N5dWeS8p09k/download",
  "https://images.unsplash.com/uploads/14122811862445bc266cf/931448f2?ixlib=rb-0.3.5&q=80&fm=jpg&crop=entropy&s=0069d7e763e0f84796cfb91191f46ddc"
 ],
 "ext": "jpeg",
 "from": "findaphoto",
 "created": 1456917795,
 "tags": [
  "img:exif",
  "ear",
  "frost",
  "grass",
  "light",
  "nature",
  "outdoors",
  "reed",
  "seed",
  "sky",
  "snow",
  "summer",
  "sun",
  "sunlight",
  "sunset",
  "tree",
  "water",
  "wheat",
  "wind",
  "winter"
 ]
}