{
 "sha1": "2920d472e8414bb5f08afa5e0985acf276aae9f0",
 "lic": "pd",
 "url": "https://images.unsplash.com/photo-1446867220627-6554405579cd",
 "urls": [
  "https://unsplash.com/photos/mBejcg00--Q/download",
  "https://images.unsplash.com/photo-1446867220627-6554405579cd?ixlib=rb-0.3.5&q=80&fm=jpg&crop=entropy&s=68cf24e3dd0fa68301adf5a90487dcb7"
 ],
 "ext": "jpeg",
 "from": "findaphoto",
 "created": 1456916941,
 "tags": [
  "img:exif",
  "autumn",
  "daytime",
  "environment",
  "evergreen",
  "fall",
  "fog",
  "forest",
  "hill",
  "landscape",
  "lush",
  "mist",
  "mountain",
  "outdoors",
  "scenic",
  "travel",
  "tree",
  "valley",
  "water",
  "wood",
  "woodland"
 ]
}