{
 "sha1": "f6a3d3bfad55e2b6ff0f3e9b5605edf4cc5346d0",
 "lic": "cc-by-sa-3.0",
 "url": "https://upload.wikimedia.org/wikipedia/en/c/ca/Old_alignment_of_Highway_5.png",
 "ext": "png",
 "from": "wiki",
 "created": 1458507659,
 "name": "Old alignment of Highway 5",
 "desc": {
  "url": "https://en.wikipedia.org/w/index.php?curid=33285165",
  "html": "<p>An abandoned section of <a href=\"//en.wikipedia.org/wiki/Ontario_Highway_5\" title=\"Ontario Highway 5\">Ontario Highway 5</a> sits in the bushes alongside the current route,\n</p>"
 },
 "wiki": {
  "DateTime": "2011-10-03 02:55:34",
  "Credit": "<p>Own work\n</p>",
  "DateTimeOriginal": "<p>October 1, 2011\n</p>",
  "Artist": "<b><a href=\"//en.wikipedia.org/wiki/User:Floydian\" title=\"User:Floydian\"><font color=\"#5A5AC5\">ʄɭoʏɗiaɲ</font></a></b> <sup><a href=\"//en.wikipedia.org/wiki/User_talk:Floydian\" title=\"User talk:Floydian\"><font color=\"#3AAA3A\">τ</font></a></sup><sub><a href=\"//en.wikipedia.org/wiki/Special:Contributions/Floydian\" title=\"Special:Contributions/Floydian\"><font color=\"#3AAA3A\">¢</font></a></sub>",
  "UsageTerms": "Creative Commons Attribution-ShareAlike 3.0",
  "AttributionRequired": "true",
  "LicenseUrl": "http://creativecommons.org/licenses/by-sa/3.0/"
 }
}