{
 "sha1": "7310c09094371e70270b75396a41bc472cfccbe3",
 "lic": "pd",
 "url": "https://images.unsplash.com/uploads/1411818826407782c4fb9/e6385921",
 "urls": [
  "https://unsplash.com/photos/5a5_ffZrD1o/download",
  "https://images.unsplash.com/uploads/1411818826407782c4fb9/e6385921?ixlib=rb-0.3.5&q=80&fm=jpg&crop=entropy&s=46f7ff70e98988c272d09e038b023624"
 ],
 "ext": "jpeg",
 "from": "findaphoto",
 "created": 1456916146,
 "tags": [
  "animal",
  "blur",
  "bug",
  "caterpillar",
  "dew",
  "dof",
  "fall",
  "flower",
  "forest",
  "grass",
  "insect",
  "invertebrate",
  "morning",
  "nature",
  "plant",
  "spider",
  "summer",
  "sunset",
  "water",
  "wildlife"
 ]
}