{
 "sha1": "ca8fe1c763452a7dea1598a132ea2a560b6ba4eb",
 "lic": "pd",
 "url": "https://images.unsplash.com/photo-1429091967365-492aaa5accfe",
 "urls": [
  "https://unsplash.com/photos/ZQeRH1XD4Tc/download",
  "https://images.unsplash.com/photo-1429091967365-492aaa5accfe?ixlib=rb-0.3.5&q=80&fm=jpg&crop=entropy&s=2d04b5654341a07e9c9af2821a187bb6"
 ],
 "ext": "jpeg",
 "from": "findaphoto",
 "created": 1456906165,
 "tags": [
  "fog",
  "forest",
  "hiking",
  "landscape",
  "mist",
  "mountain",
  "national park",
  "nature",
  "outdoors",
  "river",
  "rock",
  "sierra nevada",
  "snow",
  "travel",
  "tree",
  "water",
  "waterfall",
  "yosemite",
  "yosemite national park"
 ]
}