{
 "sha1": "90054cd2130aba0c3e7f4159bf16ad44ce6ce1bf",
 "lic": "pd",
 "url": "https://images.unsplash.com/photo-1436377037450-1b1bb5ba3c60",
 "urls": [
  "https://unsplash.com/photos/8EwXo2mHtjs/download",
  "https://images.unsplash.com/photo-1436377037450-1b1bb5ba3c60?ixlib=rb-0.3.5&q=80&fm=jpg&crop=entropy&s=1a945d18e42bfd38e1429e9cd34177ef"
 ],
 "ext": "jpeg",
 "from": "findaphoto",
 "created": 1456880436,
 "tags": [
  "img:exif",
  "aeroplane",
  "air",
  "aircraft",
  "airplane",
  "backlit",
  "cloud",
  "dawn",
  "dusk",
  "evening",
  "flight",
  "fly",
  "hawk",
  "jet",
  "nature",
  "plane",
  "silhouette",
  "sky",
  "sun",
  "sunrise",
  "sunset",
  "transport"
 ]
}