{
 "sha1": "bc18cb15e507cab63460346c7f030a4af8d5fdbc",
 "lic": "pd",
 "url": "https://images.unsplash.com/photo-1429857950654-539591eef320",
 "urls": [
  "https://unsplash.com/photos/inbgmkY76ps/download",
  "https://images.unsplash.com/photo-1429857950654-539591eef320?ixlib=rb-0.3.5&q=80&fm=jpg&crop=entropy&s=96b796bfa2f4876baa047930bdac3007"
 ],
 "ext": "jpeg",
 "from": "findaphoto",
 "created": 1456916270,
 "tags": [
  "auto",
  "blur",
  "fast",
  "hallway",
  "metro",
  "motion",
  "move",
  "movement",
  "perspective",
  "reflection",
  "road",
  "speed",
  "station",
  "subway",
  "traffic",
  "transportation",
  "tunnel",
  "underground",
  "way",
  "zoom"
 ]
}