{
 "sha1": "30054e496685b3ccfa0559fae1426d75eb322a72",
 "lic": "cc-by-sa-3.0",
 "url": "https://upload.wikimedia.org/wikipedia/en/6/6f/Dave_Rubin_at_Politicon_in_Los_Angeles%2C_October_2015.png",
 "ext": "png",
 "from": "wiki",
 "created": 1458507657,
 "name": "Dave Rubin at Politicon in Los Angeles, October 2015",
 "desc": {
  "url": "https://en.wikipedia.org/w/index.php?curid=48483196",
  "html": "<p>Dave Rubin during a live taping of his show The Rubin Report at Politicon in Los Angeles in October 2015. He is talking with former head of the RNC Michael Steele.\n</p>"
 },
 "wiki": {
  "DateTime": "2015-11-07 01:42:11",
  "Credit": "<p>I took this photo during a live taping of The Rubin Report, a show that I produce and own.\n</p>",
  "DateTimeOriginal": "<p>2015-10-16\n</p>",
  "Artist": "<p><a href=\"//en.wikipedia.org/w/index.php?title=User:DavidJanet88&amp;action=edit&amp;redlink=1\" class=\"new\" title=\"User:DavidJanet88 (page does not exist)\">DavidJanet88</a>\n</p>",
  "UsageTerms": "Creative Commons Attribution-ShareAlike 3.0",
  "AttributionRequired": "true",
  "LicenseUrl": "http://creativecommons.org/licenses/by-sa/3.0/"
 }
}