{
 "sha1": "306b2d40baae1a2540e1556152c8f6fe9c8b4052",
 "lic": "pd",
 "url": "http://skitterphoto.com/?ddownload=35710",
 "urls": [
  "http://skitterphoto.com/?ddownload=35710"
 ],
 "ext": "jpeg",
 "from": "findaphoto",
 "created": 1456880137,
 "tags": [
  "analog",
  "antique",
  "bellows",
  "classic",
  "electronics",
  "equipment",
  "lens",
  "lenses",
  "modern",
  "music",
  "nostalgia",
  "obsolete",
  "old",
  "retro",
  "sound",
  "technology",
  "viewfinder",
  "vintage",
  "volume",
  "img:png8 lossless"
 ]
}