{
 "sha1": "f8c36bd373aed9bfe573ecdd86e66408e3f5e0e7",
 "lic": "pd",
 "url": "https://images.unsplash.com/photo-1440470177828-6381dc5074ba",
 "urls": [
  "https://unsplash.com/photos/jgLTHYKnd5Q/download",
  "https://images.unsplash.com/photo-1440470177828-6381dc5074ba?ixlib=rb-0.3.5&q=80&fm=jpg&crop=entropy&s=bf486126df3f76dec8681c99d199696b"
 ],
 "ext": "jpeg",
 "from": "findaphoto",
 "created": 1456906563,
 "tags": [
  "img:exif",
  "img:compressed",
  "cloud",
  "conifer",
  "daytime",
  "environment",
  "fog",
  "forest",
  "hiking",
  "hill",
  "landscape",
  "mountain",
  "nature",
  "outdoors",
  "ridge",
  "scenic",
  "sky",
  "travel",
  "tree",
  "valley",
  "woodland"
 ]
}