{
 "sha1": "a1b470ee875511d808c095aace85f874876c5eab",
 "lic": "pd",
 "url": "https://images.unsplash.com/photo-1446960040713-06c33df11426",
 "urls": [
  "https://unsplash.com/photos/TYQ380qlcgA/download",
  "https://images.unsplash.com/photo-1446960040713-06c33df11426?ixlib=rb-0.3.5&q=80&fm=jpg&crop=entropy&s=2a0acb3c75f6bb1319a29318aaa11e9b"
 ],
 "ext": "jpeg",
 "from": "findaphoto",
 "created": 1456905577,
 "tags": [
  "agriculture",
  "animal",
  "autumn",
  "bovine",
  "cattle",
  "countryside",
  "cow",
  "fall",
  "farm",
  "field",
  "goat",
  "grass",
  "horse",
  "landscape",
  "livestock",
  "mammal",
  "meadow",
  "outdoors",
  "pasture",
  "ranch",
  "two"
 ]
}