{
 "sha1": "ef7f2d29424395f5505357b7bbaabfebf85713e2",
 "lic": "pd",
 "url": "https://images.unsplash.com/photo-1420768797814-f484a81f6be0",
 "urls": [
  "https://unsplash.com/photos/uAyb-u59pyA/download",
  "https://images.unsplash.com/photo-1420768797814-f484a81f6be0?ixlib=rb-0.3.5&q=80&fm=jpg&crop=entropy&s=a0918306855b309dccd391c42e1dea0f"
 ],
 "ext": "jpeg",
 "from": "findaphoto",
 "created": 1456904670,
 "tags": [
  "img:exif",
  "animal",
  "antarctica",
  "galapagos",
  "head",
  "lion",
  "marine",
  "nature",
  "nest",
  "ocean",
  "outdoors",
  "portrait",
  "river",
  "rock",
  "sea",
  "sea lion",
  "seal",
  "water",
  "wildlife",
  "zoo"
 ]
}