{
 "sha1": "6da8e365a8578b0afe4bd7f29b2d182a02013f60",
 "lic": "pd",
 "url": "https://images.unsplash.com/photo-1453194843300-a81c8142e9fa",
 "urls": [
  "https://unsplash.com/photos/NecO3b7UGY4/download",
  "https://images.unsplash.com/photo-1453194843300-a81c8142e9fa?ixlib=rb-0.3.5&q=80&fm=jpg&crop=entropy&s=3a72dc5f4aebd1b53166c8c2c76d10f8"
 ],
 "ext": "jpeg",
 "from": "findaphoto",
 "created": 1456915663,
 "tags": [
  "architecture",
  "automobile",
  "building",
  "business",
  "car",
  "city",
  "cityscape",
  "highway",
  "hotel",
  "intersection",
  "road",
  "skyscraper",
  "street",
  "traffic",
  "traffic jam",
  "transport",
  "transportation",
  "travel",
  "urban",
  "vehicle"
 ]
}