{
 "sha1": "e59d71f12f81bead092b83d7027cf0b48513400f",
 "lic": "pd",
 "url": "https://upload.wikimedia.org/wikipedia/en/c/c8/Renner%2C_TX_1974_Composite.png",
 "ext": "png",
 "from": "wiki",
 "created": 1458507659,
 "name": "Renner, TX 1974 Composite",
 "desc": {
  "url": "https://en.wikipedia.org/w/index.php?curid=37651989",
  "html": "<p>A Map Showing the corporate boundaries of Renner c. 1974. Large road in left section is Old Denton Road.\n</p>"
 },
 "tags": [
  "united states geological survey images"
 ]
}