{
 "sha1": "f306b397bd739fccd9f663f44166e2fef3183fac",
 "lic": "cc-by-sa-3.0",
 "url": "https://upload.wikimedia.org/wikipedia/en/8/8d/Dollis_valley_greenwalk_post.png",
 "ext": "png",
 "from": "wiki",
 "created": 1458507657,
 "name": "Dollis valley greenwalk post",
 "desc": {
  "url": "https://en.wikipedia.org/w/index.php?curid=23171187",
  "html": "<p>Dollis Valley Geenwalk post\n</p>"
 },
 "wiki": {
  "DateTime": "2009-06-10 17:47:08",
  "Credit": "<p>I created this work entirely by myself.\n</p>",
  "DateTimeOriginal": "<p>June 2009\n</p>",
  "Artist": "<p><a href=\"//en.wikipedia.org/wiki/User:Grim23\" title=\"User:Grim23\">Grim23</a> (<a href=\"//en.wikipedia.org/wiki/User_talk:Grim23\" title=\"User talk:Grim23\">talk</a>)\n</p>",
  "UsageTerms": "Creative Commons Attribution-ShareAlike 3.0",
  "AttributionRequired": "true",
  "LicenseUrl": "http://creativecommons.org/licenses/by-sa/3.0/"
 }
}