{
 "sha1": "2eb7507d859206b5e604547ada554e9c3fbf8560",
 "lic": "pd",
 "url": "http://www.lifeofpix.com/wp-content/uploads/2015/07/Life-of-Pix-free-stock-photos-stadstill-new-york-cars-nabeel.jpg",
 "ext": "jpeg",
 "from": "findaphoto",
 "created": 1456915453,
 "name": "stadstill new york cars nabeel",
 "tags": [
  "accident",
  "adult",
  "automobile",
  "blur",
  "city",
  "industrial",
  "industry",
  "interaction",
  "men",
  "people",
  "police",
  "politics",
  "protest",
  "road",
  "store",
  "street",
  "taxi",
  "traffic",
  "transportation",
  "travel",
  "urban",
  "vehicle"
 ]
}