{
 "sha1": "8f08b24a3f81930b4629e16b3959ff002e3c2fe4",
 "lic": "pd",
 "url": "https://images.unsplash.com/photo-1424036879571-fdc0aeccd7fe",
 "urls": [
  "https://unsplash.com/photos/kKz0oym0XpQ/download",
  "https://images.unsplash.com/photo-1424036879571-fdc0aeccd7fe?ixlib=rb-0.3.5&q=80&fm=jpg&crop=entropy&s=9c14df04f230c949ae014a7c836398c9"
 ],
 "ext": "png",
 "from": "findaphoto",
 "created": 1456915870,
 "tags": [
  "blur",
  "branch",
  "conifer",
  "dof",
  "evergreen",
  "fern",
  "fir",
  "flora",
  "forest",
  "garden",
  "leaf",
  "leaves",
  "nature",
  "needle",
  "pine",
  "plant",
  "rain",
  "spruce",
  "summer",
  "tree"
 ]
}