{
 "sha1": "835c25ecf48614054df45e5fbb6d64a55ce5be7f",
 "lic": "pd",
 "url": "https://images.unsplash.com/photo-1450862479751-84eeaf2fcca4",
 "urls": [
  "https://unsplash.com/photos/FHEH2jQgLVk/download",
  "https://images.unsplash.com/photo-1450862479751-84eeaf2fcca4?ixlib=rb-0.3.5&q=80&fm=jpg&crop=entropy&s=f91565abdd0d82574477998b58b385c8"
 ],
 "ext": "jpeg",
 "from": "findaphoto",
 "created": 1456882164,
 "tags": [
  "bakery",
  "baking",
  "chef",
  "cooking",
  "croissant",
  "daytime",
  "dough",
  "food",
  "handmade",
  "indoors",
  "pastry",
  "rustic",
  "still life",
  "table",
  "tray"
 ]
}