{
 "sha1": "01591bb5f671523aeb47373c93f73a5621b6c6a7",
 "lic": "pd",
 "url": "https://upload.wikimedia.org/wikipedia/en/6/64/CBBM18_460.png",
 "ext": "png",
 "from": "wiki",
 "created": 1458507657,
 "name": "CBBM18 460",
 "desc": {
  "url": "https://en.wikipedia.org/w/index.php?curid=39504674",
  "html": "<p><i>Campophilus imperialis</i> [<i>sic</i>] <small>(Gould)</small> = <i><a href=\"//en.wikipedia.org/wiki/Campephilus_imperialis\" title=\"Campephilus imperialis\" class=\"mw-redirect\">Campephilus imperialis</a></i> <small>(Gould, 1832)</small>\n<b>English:</b>  Imperial Woodpecker, part of central rectrix from ventral\n</p>"
 },
 "tags": [
  "images of birds"
 ]
}