{
 "sha1": "015d4b8a3c8f80e2edeb2e3736b67f797a85b63d",
 "lic": "cc-by-sa-3.0",
 "url": "https://upload.wikimedia.org/wikipedia/en/2/25/Powers_catholic_front.png",
 "ext": "png",
 "from": "wiki",
 "created": 1458507659,
 "name": "Powers catholic front",
 "desc": {
  "url": "https://en.wikipedia.org/w/index.php?curid=47446441",
  "html": "<p>powers catholic front, from W Court\n</p>"
 },
 "wiki": {
  "DateTime": "2015-08-06 13:20:56",
  "Credit": "<p>Own work\n</p>",
  "DateTimeOriginal": "<p>2015-08-06\n</p>",
  "Artist": "<p><a href=\"//en.wikipedia.org/w/index.php?title=User:Dark0mm112&amp;action=edit&amp;redlink=1\" class=\"new\" title=\"User:Dark0mm112 (page does not exist)\">Dark0mm112</a>\n</p>",
  "UsageTerms": "Creative Commons Attribution-ShareAlike 3.0",
  "AttributionRequired": "true",
  "LicenseUrl": "http://creativecommons.org/licenses/by-sa/3.0/"
 }
}