{
 "sha1": "6b61a6e6cc987659d37f00eaa1d58a3bacf8e4dc",
 "lic": "pd",
 "url": "https://images.unsplash.com/photo-1454972806475-64f0d7f246d4",
 "urls": [
  "https://unsplash.com/photos/0Lhi5lAEvkE/download",
  "https://images.unsplash.com/photo-1454972806475-64f0d7f246d4?ixlib=rb-0.3.5&q=80&fm=jpg&crop=entropy&s=7382e45adf00df44be6cefffe7126900"
 ],
 "ext": "jpeg",
 "from": "findaphoto",
 "created": 1456904990,
 "tags": [
  "architecture",
  "ceiling",
  "chandelier",
  "church",
  "decoration",
  "dome",
  "gold",
  "hotel",
  "indoors",
  "landmark",
  "light",
  "mosque",
  "museum",
  "ottoman",
  "palace",
  "religion",
  "tourism",
  "travel",
  "window"
 ]
}