{
 "sha1": "0082c00432d62a0d83366afc173ddf4dc6131442",
 "lic": "cc-by-3.0",
 "url": "https://upload.wikimedia.org/wikipedia/en/0/09/Dr._Ferguson_and_Dr_Boughton.png",
 "ext": "png",
 "from": "wiki",
 "created": 1458507657,
 "name": "Dr. Ferguson and Dr Boughton",
 "desc": {
  "url": "https://en.wikipedia.org/w/index.php?curid=32619133",
  "html": "<p>Dr. Ferguson and Dr. Boughton with a group of ex-service patients, waiting for the arrival of their Majesties King George VI and Queen Elizabeth in June, 1939.\n</p>"
 },
 "tags": [
  "img:alpha"
 ],
 "wiki": {
  "DateTime": "2011-08-02 23:15:24",
  "Credit": "<p>Valley Echo, Volume XLV, March, 1964\n</p>",
  "DateTimeOriginal": "<p>23:15, 2 August 2011 (UTC)\n</p>",
  "Artist": "<p>unknown\n</p>",
  "UsageTerms": "Creative Commons Attribution 3.0",
  "AttributionRequired": "true",
  "LicenseUrl": "http://creativecommons.org/licenses/by/3.0/"
 }
}