{
 "sha1": "522dc309f1f335a788bbd98eac64ffb984302dc5",
 "lic": "cc-by-sa-3.0",
 "url": "https://upload.wikimedia.org/wikipedia/en/0/0f/CBC_Monkstown%2C_2014_building.png",
 "ext": "png",
 "from": "wiki",
 "created": 1458507657,
 "name": "CBC Monkstown, 2014 building",
 "desc": {
  "url": "https://en.wikipedia.org/w/index.php?curid=44425230",
  "html": "<p>New building on CBC Monkstown's grounds, completed in April 2014.\n</p>"
 },
 "wiki": {
  "DateTime": "2014-11-17 12:20:24",
  "Credit": "<p>Photo on college grounds\n</p>",
  "DateTimeOriginal": "<p>14/05/2014\n</p>",
  "Artist": "<p><a href=\"//en.wikipedia.org/wiki/User:Legiglass\" title=\"User:Legiglass\">Legiglass</a>\n</p>",
  "UsageTerms": "Creative Commons Attribution-ShareAlike 3.0",
  "AttributionRequired": "true",
  "LicenseUrl": "http://creativecommons.org/licenses/by-sa/3.0/"
 }
}