{
 "sha1": "d3a2be8482eeefefb70d1debdcd61aead3770a58",
 "lic": "cc-by-sa-4.0",
 "url": "https://upload.wikimedia.org/wikipedia/en/e/ea/TechTrade_2014_Coinfloor.png",
 "ext": "png",
 "from": "wiki",
 "created": 1458507660,
 "name": "TechTrade 2014 Coinfloor",
 "desc": {
  "url": "https://en.wikipedia.org/w/index.php?curid=44128152",
  "html": "<p>Mark Lamb, Coinfloor's CEO, speaking at TradeTech 2014 in Paris.\n</p>"
 },
 "wiki": {
  "DateTime": "2014-10-16 13:13:31",
  "Credit": "<p><a rel=\"nofollow\" class=\"external free\" href=\"http://blog.coinfloor.co.uk/post/82369442778/coinfloor-announces-otc-market-at-trade-tech\">http://blog.coinfloor.co.uk/post/82369442778/coinfloor-announces-otc-market-at-trade-tech</a>\n</p>",
  "Permission": "<table class=\"plainlinks imbox imbox-notice\" role=\"presentation\"><tr>\n<td class=\"mbox-image\"><a href=\"//en.wikipedia.org/wiki/File:OTRS_Wikimedia.svg\" class=\"image\" title=\"OTRS icon\"><img alt=\"OTRS icon\" src=\"//upload.wikimedia.org/wikipedia/commons/thumb/1/1d/OTRS_Wikimedia.svg/100px-OTRS_Wikimedia.svg.png\" width=\"100\" height=\"54\" srcset=\"//upload.wikimedia.org/wikipedia/commons/thumb/1/1d/OTRS_Wikimedia.svg/150px-OTRS_Wikimedia.svg.png 1.5x, //upload.wikimedia.org/wikipedia/commons/thumb/1/1d/OTRS_Wikimedia.svg/200px-OTRS_Wikimedia.svg.png 2x\" data-file-width=\"120\" data-file-height=\"65\"></a></td>\n<td class=\"mbox-text\">The permission for use of this work has been archived in <a href=\"//meta.wikimedia.org/wiki/OTRS\" class=\"extiw\" title=\"m:OTRS\">the Wikimedia OTRS system</a>; it is available <span class=\"plainlinksneverexpand\">as <b><a class=\"external text\" href=\"https://ticket.wikimedia.org/otrs/index.pl?Action=AgentTicketZoom&amp;TicketNumber=2014101610018693\">ticket 2014101610018693</a></b></span> for users with an OTRS account. To confirm the permission, please contact OTRS volunteers at their <a href=\"//en.wikipedia.org/wiki/Wikipedia:OTRS_noticeboard\" title=\"Wikipedia:OTRS noticeboard\">noticeboard</a>. <span id=\"field-otrs\" title=\"{{{1}}}\"></span>\n</td>\n</tr></table>\n<p><br></p>",
  "UsageTerms": "Creative Commons Attribution-ShareAlike 4.0",
  "AttributionRequired": "true",
  "LicenseUrl": "http://creativecommons.org/licenses/by-sa/4.0/"
 }
}