{
 "sha1": "e441a206d2649ffc2564fc1969f96e70a80ffc21",
 "lic": "cc-by-sa-3.0",
 "url": "https://upload.wikimedia.org/wikipedia/en/1/1b/Bristol_Engine_1.PNG",
 "ext": "png",
 "from": "wiki",
 "created": 1458507657,
 "name": "Bristol Engine 1",
 "desc": {
  "url": "https://en.wikipedia.org/w/index.php?curid=15665824",
  "html": "Bristol, CT\n<p>Bristol Engine 1\n</p>"
 },
 "wiki": {
  "DateTime": "2008-02-09 04:17:01",
  "Credit": "<p>self-made\n</p>",
  "DateTimeOriginal": "<p>Summer 2007\n</p>",
  "Artist": "<p><a href=\"//en.wikipedia.org/w/index.php?title=User:Weatherman_Tyler&amp;action=edit&amp;redlink=1\" class=\"new\" title=\"User:Weatherman Tyler (page does not exist)\">Weatherman Tyler</a> (<a href=\"//en.wikipedia.org/wiki/User_talk:Weatherman_Tyler\" title=\"User talk:Weatherman Tyler\">talk</a>)\n</p>",
  "Permission": "<p>Be sure to sight my info - \"Tyler J. - Bristol, CT\"\n</p>\n<p><br></p>",
  "UsageTerms": "Creative Commons Attribution-ShareAlike 3.0",
  "AttributionRequired": "true",
  "LicenseUrl": "http://creativecommons.org/licenses/by-sa/3.0/"
 }
}