{
 "sha1": "263c64cef337eedab1fb95616c2c31097127c37e",
 "lic": "cc-by-sa-3.0",
 "url": "https://upload.wikimedia.org/wikipedia/en/3/36/2013_Woodlands_Wellington_First_Team.jpg",
 "ext": "jpeg",
 "from": "wiki",
 "created": 1458507656,
 "name": "2013 Woodlands Wellington First Team",
 "desc": {
  "url": "https://en.wikipedia.org/w/index.php?curid=39335334",
  "html": "<p>The starting eleven for Woodlands Wellington FC on 2 May 2013 against Balestier Khalsa FC in the S.League.\n</p>"
 },
 "tags": [
  "img:exif"
 ],
 "wiki": {
  "DateTime": "2013-05-08 13:14:59",
  "Credit": "<p>Own work\n</p>",
  "DateTimeOriginal": "<p>2013-05-02\n</p>",
  "Artist": "<p><a href=\"//en.wikipedia.org/wiki/User:Six.stomachs\" title=\"User:Six.stomachs\">Six.stomachs</a>\n</p>",
  "UsageTerms": "Creative Commons Attribution-ShareAlike 3.0",
  "AttributionRequired": "true",
  "LicenseUrl": "http://creativecommons.org/licenses/by-sa/3.0/"
 }
}