{
 "sha1": "085aec9d4d7f0bb3072d4648885549585f71df42",
 "lic": "cc-by-sa-3.0",
 "url": "https://upload.wikimedia.org/wikipedia/en/c/c2/BakhtBaidar.png",
 "ext": "png",
 "from": "wiki",
 "created": 1458507657,
 "name": "BakhtBaidar",
 "desc": {
  "url": "https://en.wikipedia.org/w/index.php?curid=41074798",
  "html": "<p>Bakht Baidar at a Qoumi Watan Party Jalsa.\n</p>"
 },
 "wiki": {
  "DateTime": "2013-11-13 22:13:29",
  "Credit": "<p>Captured in the Jalsa\n</p>",
  "DateTimeOriginal": "<p>2013-05-11\n</p>",
  "Artist": "<p><a href=\"//en.wikipedia.org/w/index.php?title=User:Mycontributions2wiki&amp;action=edit&amp;redlink=1\" class=\"new\" title=\"User:Mycontributions2wiki (page does not exist)\">Mycontributions2wiki</a>\n</p>",
  "UsageTerms": "Creative Commons Attribution-ShareAlike 3.0",
  "AttributionRequired": "true",
  "LicenseUrl": "http://creativecommons.org/licenses/by-sa/3.0/"
 }
}