{
 "sha1": "9edf3f4dc9c3db3800b86a315f778b3a25a0773d",
 "lic": "pd",
 "url": "https://images.unsplash.com/photo-1455382054916-9c12746cfb43",
 "urls": [
  "https://unsplash.com/photos/VKPAzDovWKU/download",
  "https://images.unsplash.com/photo-1455382054916-9c12746cfb43?ixlib=rb-0.3.5&q=80&fm=jpg&crop=entropy&s=5fc01024a46ac91094fcd0e905af7dcd"
 ],
 "ext": "jpeg",
 "from": "findaphoto",
 "created": 1456905821,
 "tags": [
  "architecture",
  "building",
  "door",
  "historic",
  "holiday",
  "home",
  "hotel",
  "house",
  "light",
  "museum",
  "old",
  "outdoors",
  "road",
  "street",
  "travel",
  "tree",
  "tropical",
  "typical",
  "vacation",
  "view",
  "vintage",
  "window"
 ]
}