{
 "sha1": "f996eed9a23d722de2c5ba122c41ec159528ec1a",
 "lic": "cc-by-sa-3.0",
 "url": "https://upload.wikimedia.org/wikipedia/en/f/f7/Graffiti_Reclamation_Patches.jpg",
 "ext": "jpeg",
 "from": "wiki",
 "created": 1458507658,
 "name": "Graffiti Reclamation Patches",
 "desc": {
  "url": "https://en.wikipedia.org/w/index.php?curid=38302460",
  "html": "<p>Graffiti Control efforts on the border between Brooklyn and Queens.\n</p>"
 },
 "wiki": {
  "DateTime": "2013-01-22 23:39:12",
  "Credit": "<p>Created during a walk on the border of Brooklyn and Queens.<br><b>Previously published:</b> <a rel=\"nofollow\" class=\"external free\" href=\"http://worldisdoing.tumblr.com/post/36319297190\">http://worldisdoing.tumblr.com/post/36319297190</a>\n</p>",
  "DateTimeOriginal": "<p>2013-01-13\n</p>",
  "Artist": "<p><a href=\"//en.wikipedia.org/wiki/User:Carytijerina\" title=\"User:Carytijerina\">Carytijerina</a>\n</p>",
  "UsageTerms": "Creative Commons Attribution-ShareAlike 3.0",
  "AttributionRequired": "true",
  "LicenseUrl": "http://creativecommons.org/licenses/by-sa/3.0/"
 }
}