{
 "sha1": "f9ab8fd26c8a54a8e0495f026059104d0de8994a",
 "lic": "cc-by-sa-3.0",
 "url": "https://upload.wikimedia.org/wikipedia/en/5/52/KL6_At_Kirkfield.png",
 "ext": "png",
 "from": "wiki",
 "created": 1458507658,
 "name": "KL6 At Kirkfield",
 "desc": {
  "url": "https://en.wikipedia.org/w/index.php?curid=24726009",
  "html": "<p><a href=\"//en.wikipedia.org/wiki/Kawartha_Lakes_Road_6\" title=\"Kawartha Lakes Road 6\" class=\"mw-redirect\">Kawartha Lakes Road 6</a> passes beneath the <a href=\"//en.wikipedia.org/wiki/Trent%E2%80%93Severn_Waterway\" title=\"Trent–Severn Waterway\">Trent–Severn Waterway</a> at the <a href=\"//en.wikipedia.org/wiki/Kirkfield_Lift_Lock\" title=\"Kirkfield Lift Lock\">Kirkfield Lift Locks</a>.\n</p>"
 },
 "wiki": {
  "DateTime": "2009-10-17 16:59:44",
  "Credit": "<p>I (<b><a href=\"//en.wikipedia.org/wiki/User:Floydian\" title=\"User:Floydian\"><font color=\"#5A5AC5\">ʄɭoʏɗiaɲ</font></a></b> <sup><a href=\"//en.wikipedia.org/wiki/User_talk:Floydian\" title=\"User talk:Floydian\"><font color=\"#3AAA3A\">τ</font></a></sup><sub><a href=\"//en.wikipedia.org/wiki/Special:Contributions/Floydian\" title=\"Special:Contributions/Floydian\"><font color=\"#3AAA3A\">¢</font></a></sub>) created this work entirely by myself.\n</p>",
  "DateTimeOriginal": "<p>16:59, 17 October 2009 (UTC)\n</p>",
  "Artist": "<b><a href=\"//en.wikipedia.org/wiki/User:Floydian\" title=\"User:Floydian\"><font color=\"#5A5AC5\">ʄɭoʏɗiaɲ</font></a></b> <sup><a href=\"//en.wikipedia.org/wiki/User_talk:Floydian\" title=\"User talk:Floydian\"><font color=\"#3AAA3A\">τ</font></a></sup><sub><a href=\"//en.wikipedia.org/wiki/Special:Contributions/Floydian\" title=\"Special:Contributions/Floydian\"><font color=\"#3AAA3A\">¢</font></a></sub>",
  "UsageTerms": "Creative Commons Attribution-ShareAlike 3.0",
  "AttributionRequired": "true",
  "LicenseUrl": "http://creativecommons.org/licenses/by-sa/3.0/"
 }
}