{
 "sha1": "4212eac8734ed71ad8865278fdb18b9a67e6bbe3",
 "lic": "cc0",
 "url": "https://upload.wikimedia.org/wikipedia/en/2/2c/Four_eye_color.png",
 "ext": "png",
 "from": "wiki",
 "created": 1458507658,
 "name": "Four eye color",
 "desc": {
  "url": "https://en.wikipedia.org/w/index.php?curid=43815906"
 },
 "wiki": {
  "DateTime": "2014-09-13 16:53:02",
  "UsageTerms": "Creative Commons Zero, Public Domain Dedication",
  "AttributionRequired": "false",
  "LicenseUrl": "creativecommons.org/publicdomain/zero/1.0/deed.en"
 }
}