{
 "sha1": "dfbc316860035b9537518cad050f9a80ed676968",
 "lic": "pd",
 "url": "https://images.unsplash.com/photo-1433271541715-583a00246178",
 "urls": [
  "https://unsplash.com/photos/FovRTy6Alpc/download",
  "https://images.unsplash.com/photo-1433271541715-583a00246178?ixlib=rb-0.3.5&q=80&fm=jpg&crop=entropy&s=e6cc4d217745354b01e831de674db86f"
 ],
 "ext": "jpeg",
 "from": "findaphoto",
 "created": 1456917259,
 "tags": [
  "forest",
  "grass",
  "hill",
  "lake",
  "landscape",
  "mountain",
  "nature",
  "outdoors",
  "path",
  "river",
  "rock",
  "sky",
  "stream",
  "trail",
  "travel",
  "tree",
  "valley",
  "water",
  "woodland"
 ]
}