{
 "sha1": "4f8a9c1e30105082f0f7fb9288616de94ec5b755",
 "lic": "cc-by-3.0",
 "url": "https://upload.wikimedia.org/wikipedia/en/9/98/Viola_or_violin_labelled.svg",
 "ext": "svg",
 "from": "wiki",
 "created": 1458507660,
 "name": "Viola or violin labelled",
 "desc": {
  "url": "https://en.wikipedia.org/w/index.php?curid=32850968"
 },
 "wiki": {
  "DateTime": "2011-08-24 10:21:36",
  "UsageTerms": "Creative Commons Attribution 3.0",
  "AttributionRequired": "true",
  "LicenseUrl": "http://creativecommons.org/licenses/by/3.0/"
 }
}