{
 "sha1": "1a58eb248a8f3bd33d411c076cd809e8511e0d12",
 "lic": "pd",
 "url": "https://images.unsplash.com/photo-1456689337957-34d689850f36",
 "urls": [
  "https://unsplash.com/photos/EKXcJn-divM/download",
  "https://images.unsplash.com/photo-1456689337957-34d689850f36?ixlib=rb-0.3.5&q=80&fm=jpg&crop=entropy&s=6d8658cc30e597e276ad2cf9800845ba"
 ],
 "ext": "jpeg",
 "from": "findaphoto",
 "created": 1456880466,
 "tags": [
  "adult",
  "bicycle",
  "bike",
  "city",
  "cycle",
  "cyclist",
  "one",
  "outdoors",
  "pavement",
  "people",
  "riding",
  "road",
  "sidewalk",
  "street",
  "support",
  "transport",
  "transportation",
  "travel",
  "urban",
  "vehicle",
  "wheel",
  "wheelchair"
 ]
}