{
 "sha1": "d936d2d099c7b647ec2896ed00be399838bfa97f",
 "lic": "pd",
 "url": "https://images.unsplash.com/photo-1447099681886-29d0650113eb",
 "urls": [
  "https://unsplash.com/photos/12edX9zuaq4/download",
  "https://images.unsplash.com/photo-1447099681886-29d0650113eb?ixlib=rb-0.3.5&q=80&fm=jpg&crop=entropy&s=8b0f8d85872fe7627a71ebb76c1fe5a9"
 ],
 "ext": "jpeg",
 "from": "findaphoto",
 "created": 1456917087,
 "tags": [
  "abstract",
  "architecture",
  "building",
  "business",
  "city",
  "cityscape",
  "commercial",
  "futuristic",
  "glass",
  "hotel",
  "landmark",
  "modern",
  "office",
  "reflection",
  "sky",
  "skyscraper",
  "tall",
  "travel",
  "urban"
 ]
}