{
 "sha1": "bdbbefe99c1c67ffc8bf97df000830ff3966353a",
 "lic": "pd",
 "url": "https://images.unsplash.com/photo-1437382320143-352a4a540373",
 "urls": [
  "https://unsplash.com/photos/s1q4iVYznm0/download",
  "https://images.unsplash.com/photo-1437382320143-352a4a540373?ixlib=rb-0.3.5&q=80&fm=jpg&crop=entropy&s=e6bcaea694dfbd1e3a996acc8029cbc2"
 ],
 "ext": "jpeg",
 "from": "findaphoto",
 "created": 1456915826,
 "tags": [
  "img:exif",
  "adventure",
  "daytime",
  "high",
  "hiking",
  "idyllic",
  "landscape",
  "majestic",
  "mountain",
  "outdoors",
  "pinnacle",
  "remote",
  "rock",
  "scenic",
  "sky",
  "snow",
  "summer",
  "sunshine",
  "tourism",
  "travel"
 ]
}