{
 "sha1": "44deaf6a2f416b737626f9b24912d7534c03ba05",
 "lic": "pd",
 "url": "https://images.unsplash.com/photo-1440123038859-a5de728c757b",
 "urls": [
  "https://unsplash.com/photos/Pu6yD1A6ywM/download",
  "https://images.unsplash.com/photo-1440123038859-a5de728c757b?ixlib=rb-0.3.5&q=80&fm=jpg&crop=entropy&s=156922794a0104c379603a68a45bd027"
 ],
 "ext": "jpeg",
 "from": "findaphoto",
 "created": 1456880335,
 "tags": [
  "img:exif",
  "background",
  "blur",
  "botany",
  "color",
  "detail",
  "exotic",
  "flower",
  "food",
  "fruit",
  "isolated",
  "leaf",
  "leaves",
  "medicine",
  "nature",
  "plant",
  "produce",
  "still life",
  "summer",
  "tropical"
 ]
}