{
 "sha1": "7678827db263eee4693a6b71a80fac93180b8397",
 "lic": "pd",
 "url": "https://images.unsplash.com/photo-1413912623716-e6c688db0383",
 "urls": [
  "https://unsplash.com/photos/DROwSrK20nE/download",
  "https://images.unsplash.com/photo-1413912623716-e6c688db0383?ixlib=rb-0.3.5&q=80&fm=jpg&crop=entropy&s=95b3e6ca85a26c87642ec06e908ce27f"
 ],
 "ext": "jpeg",
 "from": "findaphoto",
 "created": 1456916075,
 "tags": [
  "architecture",
  "beach",
  "building",
  "city",
  "cityscape",
  "downtown",
  "hotel",
  "lake",
  "landscape",
  "outdoors",
  "river",
  "sea",
  "sky",
  "skyline",
  "skyscraper",
  "tower",
  "travel",
  "tree",
  "urban",
  "water"
 ]
}