{
 "sha1": "994244cf4cafa37eb085eb9442ab8353ddeaf0ea",
 "lic": "pd",
 "url": "https://images.unsplash.com/photo-1441911645956-df6e9bbc5496",
 "urls": [
  "https://unsplash.com/photos/hWW-NwXfT08/download",
  "https://images.unsplash.com/photo-1441911645956-df6e9bbc5496?ixlib=rb-0.3.5&q=80&fm=jpg&crop=entropy&s=5ca83f174f6df3329f143eee9c71305d"
 ],
 "ext": "jpeg",
 "from": "findaphoto",
 "created": 1456918027,
 "tags": [
  "img:exif",
  "architecture",
  "building",
  "cathedral",
  "church",
  "city",
  "dome",
  "government",
  "landmark",
  "monument",
  "old",
  "outdoors",
  "religion",
  "sculpture",
  "sky",
  "statue",
  "tourism",
  "tower",
  "travel",
  "urban"
 ]
}