{
 "sha1": "ba508de0e4b272b403e829bda6c83de6577901b1",
 "lic": "cc-by-sa-3.0",
 "url": "https://upload.wikimedia.org/wikipedia/en/b/bb/National_Coat_of_Arms_of_Iraq.png",
 "ext": "png",
 "from": "wiki",
 "created": 1458507659,
 "name": "National Coat of Arms of Iraq",
 "desc": {
  "url": "https://en.wikipedia.org/w/index.php?curid=26794932",
  "html": "<p>National Coat of Arms of Iraq\n</p>"
 },
 "tags": [
  "img:alpha",
  "img:png24 better than jpeg90",
  "img:png8 better than jpeg90",
  "img:png8 better than jpeg75"
 ],
 "wiki": {
  "DateTime": "2010-04-02 04:21:34",
  "Credit": "<p>I (<a href=\"//en.wikipedia.org/wiki/User:BenyaminMoshe\" title=\"User:BenyaminMoshe\">BenyaminMoshe</a> (<a href=\"//en.wikipedia.org/wiki/User_talk:BenyaminMoshe\" title=\"User talk:BenyaminMoshe\">talk</a>)) created this work entirely by myself.\n</p>",
  "DateTimeOriginal": "<p>04:21, 2 April 2010 (UTC)\n</p>",
  "Artist": "<p><a href=\"//en.wikipedia.org/wiki/User:BenyaminMoshe\" title=\"User:BenyaminMoshe\">BenyaminMoshe</a> (<a href=\"//en.wikipedia.org/wiki/User_talk:BenyaminMoshe\" title=\"User talk:BenyaminMoshe\">talk</a>)\n</p>",
  "UsageTerms": "Creative Commons Attribution-ShareAlike 3.0",
  "AttributionRequired": "true",
  "LicenseUrl": "http://creativecommons.org/licenses/by-sa/3.0/"
 }
}