{
 "sha1": "b55d3cb273fb624e6f12f4e7174aa4092b3d6d1b",
 "lic": "pd",
 "url": "http://content.finda.photo/jaymantri/92097825233.jpg",
 "ext": "jpeg",
 "from": "findaphoto",
 "created": 1456880734,
 "tags": [
  "$",
  "1",
  "2",
  "3",
  "4",
  "5",
  "6",
  "7",
  "8",
  "9",
  "a",
  "alcohol",
  "art",
  "b",
  "bar",
  "board",
  "c",
  "chalk",
  "d",
  "drawing",
  "drink",
  "e",
  "f",
  "g",
  "h",
  "i",
  "k",
  "l",
  "m",
  "metal",
  "n",
  "o",
  "p",
  "pump",
  "r",
  "s",
  "sign",
  "t",
  "u",
  "w",
  "x",
  "y"
 ]
}