{
 "sha1": "b84f3b7c908f5504e92e495fa22ca1934c2719e8",
 "lic": "cc-by-3.0",
 "url": "https://upload.wikimedia.org/wikipedia/en/7/77/Chubby_Carrier_knuckleheads.png",
 "ext": "png",
 "from": "wiki",
 "created": 1458507657,
 "name": "Chubby Carrier knuckleheads",
 "desc": {
  "url": "https://en.wikipedia.org/w/index.php?curid=29900008",
  "html": "<p>Chubby Carrier after a show at Knuckleheads Saloon in Kansas City, MO, December 4, 2010\n</p>"
 },
 "wiki": {
  "DateTime": "2010-12-05 08:46:06",
  "Credit": "<p>I Chris Williams created this work entirely by myself.\n</p>",
  "DateTimeOriginal": "<p>08:46, 5 December 2010 (UTC)\n</p>",
  "Artist": "<p><a href=\"//en.wikipedia.org/wiki/User:K8_fan\" title=\"User:K8 fan\">K8 fan</a> (<a href=\"//en.wikipedia.org/wiki/User_talk:K8_fan\" title=\"User talk:K8 fan\">talk</a>)\n</p>",
  "UsageTerms": "Creative Commons Attribution 3.0",
  "AttributionRequired": "true",
  "LicenseUrl": "http://creativecommons.org/licenses/by/3.0/"
 }
}