{
 "sha1": "3af387b0a6a0ea0393bd88bcf068660999030dd6",
 "lic": "pd",
 "url": "https://images.unsplash.com/photo-1444080748397-f442aa95c3e5",
 "urls": [
  "https://unsplash.com/photos/Jztmx9yqjBw/download",
  "https://images.unsplash.com/photo-1444080748397-f442aa95c3e5?ixlib=rb-0.3.5&q=80&fm=jpg&crop=entropy&s=a22e8ad598be0dd54ade17b642017ef0"
 ],
 "ext": "jpeg",
 "from": "findaphoto",
 "created": 1456906076,
 "tags": [
  "img:exif",
  "img:color profile",
  "astronomy",
  "christmas",
  "galaxy",
  "light",
  "moon",
  "mountain",
  "mystery",
  "night",
  "outdoors",
  "outer space",
  "scenic",
  "silhouette",
  "sky",
  "snow",
  "star",
  "tree",
  "weather",
  "winter",
  "woodland"
 ]
}