{
 "sha1": "c0cfa7e7b2521de65624e84c8eec5b83dd9ad772",
 "lic": "pd",
 "url": "http://www.lifeofpix.com/wp-content/uploads/2015/05/Life-of-Pix-free-stock-photos-food-macaroon-sugar-leeroy.jpg",
 "ext": "jpeg",
 "from": "findaphoto",
 "created": 1456915458,
 "name": "food macaroon sugar leeroy",
 "tags": [
  "img:exif",
  "abundance",
  "agriculture",
  "background",
  "crop",
  "delicious",
  "dessert",
  "donut",
  "food",
  "group",
  "harvest",
  "healthy",
  "many",
  "nut",
  "pattern",
  "produce",
  "small",
  "smooth",
  "snack",
  "sweet"
 ]
}