{
 "sha1": "9365ab266b184c0722630d654b005e1207b2ce00",
 "lic": "cc-by-sa-3.0",
 "url": "https://upload.wikimedia.org/wikipedia/en/8/8a/Walter_Scott_Houston_Stellafane.png",
 "ext": "png",
 "from": "wiki",
 "created": 1458507660,
 "name": "Walter Scott Houston Stellafane",
 "desc": {
  "url": "https://en.wikipedia.org/w/index.php?curid=24985793",
  "html": "<p>Writer and <a href=\"//en.wikipedia.org/wiki/Amateur_astronomy\" title=\"Amateur astronomy\">amateur astronomer</a> <a href=\"//en.wikipedia.org/wiki/Walter_Scott_Houston\" title=\"Walter Scott Houston\">Walter Scott Houston</a> talks to a group of <a href=\"//en.wikipedia.org/wiki/Amateur_telescope_making\" title=\"Amateur telescope making\">amateur telescope makers</a> at the 1983 <a href=\"//en.wikipedia.org/wiki/Stellafane\" title=\"Stellafane\">Stellafane</a> convention.\n</p>"
 },
 "wiki": {
  "DateTime": "2009-11-06 16:33:55",
  "Credit": "<p>I (<a href=\"//en.wikipedia.org/wiki/User:Fountains_of_Bryn_Mawr\" title=\"User:Fountains of Bryn Mawr\">Fountains of Bryn Mawr</a> (<a href=\"//en.wikipedia.org/wiki/User_talk:Fountains_of_Bryn_Mawr\" title=\"User talk:Fountains of Bryn Mawr\">talk</a>)) created this work entirely by myself.\n</p>",
  "DateTimeOriginal": "<p>16:33, 6 November 2009 (UTC)\n</p>",
  "Artist": "<p><a href=\"//en.wikipedia.org/wiki/User:Fountains_of_Bryn_Mawr\" title=\"User:Fountains of Bryn Mawr\">Fountains of Bryn Mawr</a> (<a href=\"//en.wikipedia.org/wiki/User_talk:Fountains_of_Bryn_Mawr\" title=\"User talk:Fountains of Bryn Mawr\">talk</a>)\n</p>",
  "UsageTerms": "Creative Commons Attribution-ShareAlike 3.0",
  "AttributionRequired": "true",
  "LicenseUrl": "http://creativecommons.org/licenses/by-sa/3.0/"
 }
}