{
 "sha1": "8c97f67be9af988c36ab91e9601dfcc6174edf85",
 "lic": "pd",
 "url": "https://images.unsplash.com/photo-1416331108676-a22ccb276e35",
 "urls": [
  "https://unsplash.com/photos/KtOid0FLjqU/download",
  "https://images.unsplash.com/photo-1416331108676-a22ccb276e35?ixlib=rb-0.3.5&q=80&fm=jpg&crop=entropy&s=f2dc2065bbf57c890e3702a5267c002b"
 ],
 "ext": "jpeg",
 "from": "findaphoto",
 "created": 1456880965,
 "tags": [
  "img:exif",
  "img:color profile",
  "architecture",
  "building",
  "city",
  "holiday",
  "home",
  "hotel",
  "house",
  "leisure",
  "luxury",
  "outdoors",
  "patio",
  "people",
  "pool",
  "poolside",
  "recreation",
  "resort",
  "swimming pool",
  "travel",
  "tree",
  "urban",
  "vacation",
  "villa"
 ]
}